michalak_algorithm/__init__.py
michalak_algorithm/geometric/__init__.py
michalak_algorithm/geometric/analytic.py
michalak_algorithm/number/__init__.py
michalak_algorithm/number/conversion.py
michalak_algorithm/number/eratosthenes.py
michalak_algorithm/number/gcd.py
michalak_algorithm/number/utils.py
michalak_algorithm/sort.py
michalak_algorithm/text/__init__.py
michalak_algorithm/text/cipher.py
michalak_algorithm/text/utils.py
michalak_algorithm-0.1.0.dist-info/METADATA
michalak_algorithm-0.1.0.dist-info/WHEEL
michalak_algorithm-0.1.0.dist-info/RECORD
